matt/__init__.py
matt/app.py
matt/config.ini
matt/node.py
matt/tree.py
matt/version.txt
matt/iqtree/iqtree-1.6.12-Linux/bin/iqtree
matt/iqtree/iqtree-1.6.12-MacOSX/bin/iqtree
matt/iqtree/iqtree-1.6.12-Windows/bin/example.phy.log
matt/iqtree/iqtree-1.6.12-Windows/bin/iqtree-click.exe
matt/iqtree/iqtree-1.6.12-Windows/bin/iqtree.exe
matt/iqtree/iqtree-1.6.12-Windows/bin/libiomp5md.dll
matt/static/bootstrap.min.css
matt/static/bootstrap.min.js
matt/static/css.css
matt/static/example.cf
matt/static/example.nex
matt/static/example.phy
matt/static/example.treefile
matt/static/jquery-3.4.1.min.js
matt/static/js.js
matt/static/logo.png
matt/static/logo.svg
matt/static/logo_alt.png
matt/static/logo_alt.svg
matt/static/models.nex
matt/static/pagemap-readme.md
matt/static/pagemap.min.js
matt/static/popper.min.js
matt/static/snap.svg-min.js
matt/templates/index.html
phylo_matt-1.3.12.dist-info/LICENSE
phylo_matt-1.3.12.dist-info/METADATA
phylo_matt-1.3.12.dist-info/WHEEL
phylo_matt-1.3.12.dist-info/entry_points.txt
phylo_matt-1.3.12.dist-info/top_level.txt
phylo_matt-1.3.12.dist-info/RECORD
