Metadata-Version: 2.2
Name: phylo-matt
Version: 1.3.12
Summary: A Framework For Modifying And Testing Topologies
Home-page: https://github.com/BIONF/MATT
Author: Jeff Raffael Gower
Author-email: jeffgower98@gmail.com
Classifier: Programming Language :: Python :: 3
Classifier: License :: OSI Approved :: GNU General Public License v3 or later (GPLv3+)
Classifier: Operating System :: OS Independent
Requires-Python: >=3.8
License-File: LICENSE
Requires-Dist: flask>=2.0.0
Dynamic: author
Dynamic: author-email
Dynamic: classifier
Dynamic: description
Dynamic: description-content-type
Dynamic: home-page
Dynamic: requires-dist
Dynamic: requires-python
Dynamic: summary
